Finstein/__init__.py
Finstein/finbsm.py
Finstein/fincalc.py
Finstein/finhyp.py
Finstein/finspot.py
Finstein-3.2.dist-info/LICENSE
Finstein-3.2.dist-info/METADATA
Finstein-3.2.dist-info/WHEEL
Finstein-3.2.dist-info/top_level.txt
Finstein-3.2.dist-info/RECORD
