Metadata-Version: 2.1
Name: Finstein
Version: 3.2
Summary: A library for finacial calculations
Home-page: UNKNOWN
Author: Abhiraj Mengade
License: MIT
Platform: UNKNOWN
License-File: LICENSE
Requires-Dist: scipy
Requires-Dist: numpy
